<?xml version="1.0" encoding="utf-8"?>
<TextureAtlas imagePath="Purple.png">
	<!-- Created with Adobe Animate version 21.0.6.41649 -->
	<!-- http://www.adobe.com/products/animate.html -->
	<SubTexture name="PurpleDown0000" x="0" y="0" width="765" height="352" frameX="0" frameY="-11" frameWidth="765" frameHeight="363"/>
	<SubTexture name="PurpleDown0001" x="0" y="0" width="765" height="352" frameX="0" frameY="-11" frameWidth="765" frameHeight="363"/>
	<SubTexture name="PurpleDown0002" x="765" y="0" width="753" height="346" frameX="-9" frameY="-7" frameWidth="765" frameHeight="363"/>
	<SubTexture name="PurpleDown0003" x="765" y="0" width="753" height="346" frameX="-9" frameY="-7" frameWidth="765" frameHeight="363"/>
	<SubTexture name="PurpleDown0004" x="1518" y="0" width="734" height="345" frameX="-17" frameY="0" frameWidth="765" frameHeight="363"/>
	<SubTexture name="PurpleDown0005" x="1518" y="0" width="734" height="345" frameX="-17" frameY="0" frameWidth="765" frameHeight="363"/>
	<SubTexture name="PurpleDown0006" x="1518" y="0" width="734" height="345" frameX="-17" frameY="0" frameWidth="765" frameHeight="363"/>
	<SubTexture name="PurpleDown0007" x="1518" y="0" width="734" height="345" frameX="-17" frameY="0" frameWidth="765" frameHeight="363"/>
	<SubTexture name="PurpleDown0008" x="1518" y="0" width="734" height="345" frameX="-17" frameY="0" frameWidth="765" frameHeight="363"/>
	<SubTexture name="PurpleDown0009" x="1518" y="0" width="734" height="345" frameX="-17" frameY="0" frameWidth="765" frameHeight="363"/>
	<SubTexture name="PurpleDown0010" x="1518" y="0" width="734" height="345" frameX="-17" frameY="0" frameWidth="765" frameHeight="363"/>
	<SubTexture name="PurpleDown0011" x="1518" y="0" width="734" height="345" frameX="-17" frameY="0" frameWidth="765" frameHeight="363"/>
	<SubTexture name="PurpleDown0012" x="1518" y="0" width="734" height="345" frameX="-17" frameY="0" frameWidth="765" frameHeight="363"/>
	<SubTexture name="PurpleDown0013" x="1518" y="0" width="734" height="345" frameX="-17" frameY="0" frameWidth="765" frameHeight="363"/>
	<SubTexture name="PurpleIdle0000" x="2252" y="0" width="877" height="444" frameX="0" frameY="-6" frameWidth="879" frameHeight="450"/>
	<SubTexture name="PurpleIdle0001" x="2252" y="0" width="877" height="444" frameX="0" frameY="-6" frameWidth="879" frameHeight="450"/>
	<SubTexture name="PurpleIdle0002" x="3129" y="0" width="874" height="435" frameX="-2" frameY="-6" frameWidth="879" frameHeight="450"/>
	<SubTexture name="PurpleIdle0003" x="3129" y="0" width="874" height="435" frameX="-2" frameY="-6" frameWidth="879" frameHeight="450"/>
	<SubTexture name="PurpleIdle0004" x="0" y="444" width="873" height="430" frameX="-2" frameY="-3" frameWidth="879" frameHeight="450"/>
	<SubTexture name="PurpleIdle0005" x="0" y="444" width="873" height="430" frameX="-2" frameY="-3" frameWidth="879" frameHeight="450"/>
	<SubTexture name="PurpleIdle0006" x="873" y="444" width="874" height="418" frameX="-5" frameY="0" frameWidth="879" frameHeight="450"/>
	<SubTexture name="PurpleIdle0007" x="873" y="444" width="874" height="418" frameX="-5" frameY="0" frameWidth="879" frameHeight="450"/>
	<SubTexture name="PurpleIdle0008" x="1747" y="444" width="874" height="418" frameX="-5" frameY="0" frameWidth="879" frameHeight="450"/>
	<SubTexture name="PurpleIdle0009" x="1747" y="444" width="874" height="418" frameX="-5" frameY="0" frameWidth="879" frameHeight="450"/>
	<SubTexture name="PurpleIdle0010" x="1747" y="444" width="874" height="418" frameX="-5" frameY="0" frameWidth="879" frameHeight="450"/>
	<SubTexture name="PurpleIdle0011" x="1747" y="444" width="874" height="418" frameX="-5" frameY="0" frameWidth="879" frameHeight="450"/>
	<SubTexture name="PurpleIdle0012" x="1747" y="444" width="874" height="418" frameX="-5" frameY="0" frameWidth="879" frameHeight="450"/>
	<SubTexture name="PurpleIdle0013" x="1747" y="444" width="874" height="418" frameX="-5" frameY="0" frameWidth="879" frameHeight="450"/>
	<SubTexture name="PurpleLeft0000" x="2621" y="444" width="831" height="424" frameX="0" frameY="-2" frameWidth="831" frameHeight="426"/>
	<SubTexture name="PurpleLeft0001" x="2621" y="444" width="831" height="424" frameX="0" frameY="-2" frameWidth="831" frameHeight="426"/>
	<SubTexture name="PurpleLeft0002" x="0" y="874" width="805" height="410" frameX="-16" frameY="-1" frameWidth="831" frameHeight="426"/>
	<SubTexture name="PurpleLeft0003" x="0" y="874" width="805" height="410" frameX="-16" frameY="-1" frameWidth="831" frameHeight="426"/>
	<SubTexture name="PurpleLeft0004" x="805" y="874" width="748" height="382" frameX="-48" frameY="0" frameWidth="831" frameHeight="426"/>
	<SubTexture name="PurpleLeft0005" x="805" y="874" width="748" height="382" frameX="-48" frameY="0" frameWidth="831" frameHeight="426"/>
	<SubTexture name="PurpleLeft0006" x="805" y="874" width="748" height="382" frameX="-48" frameY="0" frameWidth="831" frameHeight="426"/>
	<SubTexture name="PurpleLeft0007" x="805" y="874" width="748" height="382" frameX="-48" frameY="0" frameWidth="831" frameHeight="426"/>
	<SubTexture name="PurpleLeft0008" x="805" y="874" width="748" height="382" frameX="-48" frameY="0" frameWidth="831" frameHeight="426"/>
	<SubTexture name="PurpleLeft0009" x="805" y="874" width="748" height="382" frameX="-48" frameY="0" frameWidth="831" frameHeight="426"/>
	<SubTexture name="PurpleLeft0010" x="805" y="874" width="748" height="382" frameX="-48" frameY="0" frameWidth="831" frameHeight="426"/>
	<SubTexture name="PurpleLeft0011" x="805" y="874" width="748" height="382" frameX="-48" frameY="0" frameWidth="831" frameHeight="426"/>
	<SubTexture name="PurpleLeft0012" x="805" y="874" width="748" height="382" frameX="-48" frameY="0" frameWidth="831" frameHeight="426"/>
	<SubTexture name="PurpleLeft0013" x="805" y="874" width="748" height="382" frameX="-48" frameY="0" frameWidth="831" frameHeight="426"/>
	<SubTexture name="PurpleRight0000" x="1553" y="874" width="640" height="491" frameX="-22" frameY="0" frameWidth="662" frameHeight="491"/>
	<SubTexture name="PurpleRight0001" x="1553" y="874" width="640" height="491" frameX="-22" frameY="0" frameWidth="662" frameHeight="491"/>
	<SubTexture name="PurpleRight0002" x="2193" y="874" width="637" height="483" frameX="-12" frameY="-8" frameWidth="662" frameHeight="491"/>
	<SubTexture name="PurpleRight0003" x="2193" y="874" width="637" height="483" frameX="-12" frameY="-8" frameWidth="662" frameHeight="491"/>
	<SubTexture name="PurpleRight0004" x="2830" y="874" width="630" height="472" frameX="0" frameY="-19" frameWidth="662" frameHeight="491"/>
	<SubTexture name="PurpleRight0005" x="2830" y="874" width="630" height="472" frameX="0" frameY="-19" frameWidth="662" frameHeight="491"/>
	<SubTexture name="PurpleRight0006" x="2830" y="874" width="630" height="472" frameX="0" frameY="-19" frameWidth="662" frameHeight="491"/>
	<SubTexture name="PurpleRight0007" x="2830" y="874" width="630" height="472" frameX="0" frameY="-19" frameWidth="662" frameHeight="491"/>
	<SubTexture name="PurpleRight0008" x="2830" y="874" width="630" height="472" frameX="0" frameY="-19" frameWidth="662" frameHeight="491"/>
	<SubTexture name="PurpleRight0009" x="2830" y="874" width="630" height="472" frameX="0" frameY="-19" frameWidth="662" frameHeight="491"/>
	<SubTexture name="PurpleRight0010" x="2830" y="874" width="630" height="472" frameX="0" frameY="-19" frameWidth="662" frameHeight="491"/>
	<SubTexture name="PurpleRight0011" x="2830" y="874" width="630" height="472" frameX="0" frameY="-19" frameWidth="662" frameHeight="491"/>
	<SubTexture name="PurpleRight0012" x="2830" y="874" width="630" height="472" frameX="0" frameY="-19" frameWidth="662" frameHeight="491"/>
	<SubTexture name="PurpleRight0013" x="2830" y="874" width="630" height="472" frameX="0" frameY="-19" frameWidth="662" frameHeight="491"/>
	<SubTexture name="PurpleShooting0000" x="0" y="1365" width="1120" height="390" frameX="0" frameY="-91" frameWidth="1252" frameHeight="481"/>
	<SubTexture name="PurpleShooting0001" x="1120" y="1365" width="1252" height="390" frameX="0" frameY="-91" frameWidth="1252" frameHeight="481"/>
	<SubTexture name="PurpleShooting0002" x="2372" y="1365" width="864" height="458" frameX="-1" frameY="-23" frameWidth="1252" frameHeight="481"/>
	<SubTexture name="PurpleShooting0003" x="3236" y="1365" width="855" height="472" frameX="-1" frameY="-9" frameWidth="1252" frameHeight="481"/>
	<SubTexture name="PurpleShooting0004" x="0" y="1837" width="844" height="481" frameX="-2" frameY="0" frameWidth="1252" frameHeight="481"/>
	<SubTexture name="PurpleShooting0005" x="0" y="1837" width="844" height="481" frameX="-2" frameY="0" frameWidth="1252" frameHeight="481"/>
	<SubTexture name="PurpleShooting0006" x="0" y="1837" width="844" height="481" frameX="-2" frameY="0" frameWidth="1252" frameHeight="481"/>
	<SubTexture name="PurpleShooting0007" x="0" y="1837" width="844" height="481" frameX="-2" frameY="0" frameWidth="1252" frameHeight="481"/>
	<SubTexture name="PurpleShooting0008" x="844" y="1837" width="933" height="390" frameX="-2" frameY="-91" frameWidth="1252" frameHeight="481"/>
	<SubTexture name="PurpleShooting0009" x="844" y="1837" width="933" height="390" frameX="-2" frameY="-91" frameWidth="1252" frameHeight="481"/>
	<SubTexture name="PurpleShooting0010" x="1777" y="1837" width="928" height="390" frameX="-2" frameY="-91" frameWidth="1252" frameHeight="481"/>
	<SubTexture name="PurpleShooting0011" x="1777" y="1837" width="928" height="390" frameX="-2" frameY="-91" frameWidth="1252" frameHeight="481"/>
	<SubTexture name="PurpleShooting0012" x="2705" y="1837" width="924" height="390" frameX="-2" frameY="-91" frameWidth="1252" frameHeight="481"/>
	<SubTexture name="PurpleShooting0013" x="2705" y="1837" width="924" height="390" frameX="-2" frameY="-91" frameWidth="1252" frameHeight="481"/>
	<SubTexture name="PurpleUp0000" x="734" y="2792" width="758" height="450" frameX="-6" frameY="0" frameWidth="1275" frameHeight="554"/>
	<SubTexture name="PurpleUp0001" x="734" y="2792" width="758" height="450" frameX="-6" frameY="0" frameWidth="1275" frameHeight="554"/>
	<SubTexture name="PurpleUp0002" x="3218" y="3242" width="764" height="443" frameX="0" frameY="-6" frameWidth="764" frameHeight="449"/>
	<SubTexture name="PurpleUp0003" x="3218" y="3242" width="764" height="443" frameX="0" frameY="-6" frameWidth="764" frameHeight="449"/>
	<SubTexture name="PurpleUp0004" x="2256" y="2792" width="736" height="422" frameX="-10" frameY="-26" frameWidth="1275" frameHeight="554"/>
	<SubTexture name="PurpleUp0005" x="2256" y="2792" width="736" height="422" frameX="-10" frameY="-26" frameWidth="1275" frameHeight="554"/>
	<SubTexture name="PurpleUp0006" x="2256" y="2792" width="736" height="422" frameX="-10" frameY="-26" frameWidth="1275" frameHeight="554"/>
	<SubTexture name="PurpleUp0007" x="2256" y="2792" width="736" height="422" frameX="-10" frameY="-26" frameWidth="1275" frameHeight="554"/>
	<SubTexture name="PurpleUp0008" x="2256" y="2792" width="736" height="422" frameX="-10" frameY="-26" frameWidth="1275" frameHeight="554"/>
	<SubTexture name="PurpleUp0009" x="2256" y="2792" width="736" height="422" frameX="-10" frameY="-26" frameWidth="1275" frameHeight="554"/>
	<SubTexture name="PurpleUp0010" x="2256" y="2792" width="736" height="422" frameX="-10" frameY="-26" frameWidth="1275" frameHeight="554"/>
	<SubTexture name="PurpleUp0011" x="2256" y="2792" width="736" height="422" frameX="-10" frameY="-26" frameWidth="1275" frameHeight="554"/>
	<SubTexture name="PurpleUp0012" x="2256" y="2792" width="736" height="422" frameX="-10" frameY="-26" frameWidth="1275" frameHeight="554"/>
	<SubTexture name="PurpleUp0013" x="2256" y="2792" width="736" height="422" frameX="-10" frameY="-26" frameWidth="1275" frameHeight="554"/>
</TextureAtlas>
